<?xml version="1.0" encoding="UTF-8" standalone="no"?>
<!DOCTYPE root SYSTEM "file://st01/project/A17/_Programmer/ui/uia.dtd">
<root>
	<anim name="anm_image_offset">
		<curve attr="offset_uvwh" interpolate="constant" >
			<key time="0.0"		value="0, 0, 0, 0"/>
			<key time="1.0"		value="32, 0, 0, 0"/>
			<key time="2.0"		value="64, 0, 0, 0"/>
			<key time="3.0"		value="64, 0, 0, 0"/>
		</curve>
	</anim>
	<anim name="anm_image_offset2">
		<curve attr="offset_uvwh" interpolate="linear" >
			<key time="0.0"		value="0, 0, 0, 0"/>
			<key time="1.0"		value="32, 0, 0, 0"/>
			<key time="2.0"		value="64, 0, 0, 0"/>
			<key time="3.0"		value="64, 0, 0, 0"/>
		</curve>
	</anim>
</root>

