<root>
	<effect eff_no="559" pos="190.51,-0.06,290.24" rot="-7.28,-69.64,8.99" scale="1.00,1.00,1.00"/>
	<effect eff_no="559" pos="192.72,-0.15,283.59" rot="-2.43,0.25,6.00" scale="1.00,1.00,1.00"/>
	<effect eff_no="559" pos="198.45,0.21,279.94" rot="4.94,59.32,9.24" scale="1.00,1.00,1.00"/>
	<effect eff_no="559" pos="206.41,0.04,277.96" rot="-179.16,30.00,-179.43" scale="1.00,1.00,1.00"/>
	<effect eff_no="559" pos="219.13,0.27,280.59" rot="-1.51,20.02,0.87" scale="1.00,1.00,1.00"/>
	<effect eff_no="559" pos="210.33,0.04,269.37" rot="91.21,-88.77,-90.00" scale="1.00,1.00,1.00"/>
	<effect eff_no="559" pos="205.62,0.12,264.42" rot="-17.41,69.24,-14.58" scale="1.00,1.00,1.00"/>
	<effect eff_no="559" pos="192.27,0.12,269.36" rot="170.75,29.76,176.01" scale="1.00,1.00,1.00"/>
	<effect eff_no="559" pos="181.28,0.16,265.68" rot="2.53,59.91,3.70" scale="1.00,1.00,1.00"/>
	<effect eff_no="559" pos="169.89,0.44,264.11" rot="-3.61,69.70,0.45" scale="1.00,1.00,1.00"/>
	<effect eff_no="559" pos="161.29,0.17,274.48" rot="2.65,-9.96,-1.07" scale="1.00,1.00,1.00"/>
	<effect eff_no="559" pos="154.71,0.05,284.43" rot="1.04,70.00,0.80" scale="1.00,1.00,1.00"/>
	<effect eff_no="559" pos="151.58,0.72,268.06" rot="179.22,-49.93,-177.20" scale="1.00,1.00,1.00"/>
	<effect eff_no="559" pos="161.58,2.52,246.74" rot="15.64,-79.43,-12.79" scale="1.00,1.00,1.00"/>
	<effect eff_no="559" pos="161.33,3.45,236.85" rot="177.31,-0.21,175.50" scale="1.00,1.00,1.00"/>
	<effect eff_no="559" pos="167.41,3.77,230.34" rot="-176.62,39.83,-175.86" scale="1.00,1.00,1.00"/>
	<effect eff_no="559" pos="173.89,3.72,231.19" rot="174.97,-29.87,-177.09" scale="1.00,1.00,1.00"/>
	<effect eff_no="559" pos="189.91,3.60,231.25" rot="177.23,-20.10,177.29" scale="1.00,1.00,1.00"/>
	<effect eff_no="559" pos="198.96,3.05,235.32" rot="25.85,-78.28,-28.30" scale="1.00,1.00,1.00"/>
	<effect eff_no="559" pos="211.85,2.86,231.17" rot="176.97,69.68,174.00" scale="1.00,1.00,1.00"/>
	<effect eff_no="559" pos="221.20,1.20,244.97" rot="9.29,-49.30,-9.57" scale="1.00,1.00,1.00"/>
	<effect eff_no="559" pos="213.66,0.43,257.82" rot="-174.36,-79.93,175.25" scale="1.00,1.00,1.00"/>
</root>
