<root>
	<effect eff_no="559" pos="219.34,0.86,238.52" rot="92.69,-87.28,-90.00" scale="1.00,1.00,1.00"/>
	<effect eff_no="559" pos="238.17,0.93,253.87" rot="4.76,49.88,3.97" scale="1.00,1.00,1.00"/>
	<effect eff_no="559" pos="240.87,0.58,261.35" rot="177.45,-19.99,-179.25" scale="1.00,1.00,1.00"/>
	<effect eff_no="559" pos="251.56,0.74,256.40" rot="2.79,10.02,-0.22" scale="1.00,1.00,1.00"/>
	<effect eff_no="559" pos="249.02,1.16,248.49" rot="175.81,49.85,175.56" scale="1.00,1.00,1.00"/>
	<effect eff_no="559" pos="255.48,1.24,240.39" rot="8.62,-79.64,-10.49" scale="1.00,1.00,1.00"/>
	<effect eff_no="559" pos="254.41,1.46,231.42" rot="4.35,-79.78,-6.15" scale="1.00,1.00,1.00"/>
	<effect eff_no="559" pos="247.71,1.67,224.04" rot="-179.86,-20.00,179.45" scale="1.00,1.00,1.00"/>
	<effect eff_no="559" pos="243.92,1.62,212.17" rot="-0.39,40.00,0.80" scale="1.00,1.00,1.00"/>
	<effect eff_no="559" pos="234.24,1.47,221.80" rot="-178.31,-59.95,-179.36" scale="1.00,1.00,1.00"/>
	<effect eff_no="559" pos="232.32,1.50,231.27" rot="-179.50,39.95,-177.46" scale="1.00,1.00,1.00"/>
	<effect eff_no="559" pos="257.83,1.52,220.85" rot="1.04,10.02,-1.11" scale="1.00,1.00,1.00"/>
	<effect eff_no="559" pos="233.69,0.46,265.13" rot="178.51,-20.00,-179.58" scale="1.00,1.00,1.00"/>
</root>
